ir_evaluation/__init__.py
ir_evaluation/effectiveness.py
ir_evaluation/datasets/__init__.py
ir_evaluation/datasets/data/dataset1.txt
ir_evaluation/datasets/data/dataset2.txt
ir_evaluation/datasets/data/dataset3.txt
ir_evaluation/datasets/data/dataset4.txt
ir_evaluation/datasets/data/dataset5.txt
ir_evaluation_py-1.0.0.dist-info/LICENSE
ir_evaluation_py-1.0.0.dist-info/METADATA
ir_evaluation_py-1.0.0.dist-info/WHEEL
ir_evaluation_py-1.0.0.dist-info/top_level.txt
ir_evaluation_py-1.0.0.dist-info/RECORD
