Metadata-Version: 2.1
Name: ir-evaluation-py
Version: 1.0.0
Summary: This library was created in order to evaluate the effectiveness of any kind of algorithm used in IR systems and analyze how well they perform.
Home-page: https://github.com/ozcan39/ir_evaluation_py
Author: Veli Özcan Budak
Author-email: veliozcanbudak@gmail.com
License: UNKNOWN
Keywords: information retrieval effectiveness evaluation
Platform: UNKNOWN
Classifier: Programming Language :: Python :: 3.7
Classifier: License :: OSI Approved :: GNU Lesser General Public License v2 or later (LGPLv2+)
Classifier: Operating System :: OS Independent
Requires-Python: >=3.7
